{
  "Student": [
    {
      "id": 1,
      "address": {
        "city": "aaaa",
        "blockno": "2"
      },
      "parsonalDetalis": {
        "aadhaarno": "4553451",
        "passbookno": "556545478454",
        "panno": "25695216542"
      },
      "companyname": "aaaa",
      "fname": "aaaa",
      "lname": "aaa",
      "email": "aaa",
      "mobileno": "12312333232",
      "salary": "132323"
    },
    {
      "id": 2,
      "address": {},
      "parsonalDetalis": {},
      "email": "45454545",
      "salary": "=9",
      "mobileno": "0-=0-"
    },
    {
      "id": 3,
      "address": {},
      "parsonalDetalis": {},
      "email": "]-0-0=",
      "mobileno": "===0"
    },
    {
      "id": 4,
      "address": {},
      "parsonalDetalis": {},
      "email": "90-=90=-0=",
      "mobileno": "-0=-0"
    },
    {
      "id": 5,
      "address": {},
      "parsonalDetalis": {},
      "email": "sas",
      "mobileno": "asas"
    },
    {
      "id": 6,
      "address": {},
      "parsonalDetalis": {},
      "email": "asa",
      "mobileno": "sasas"
    }
  ]
}